rbltracker/__init__.py
rbltracker/client.py
rbltracker/api/__init__.py
rbltracker/api/acls.py
rbltracker/api/check.py
rbltracker/api/contact.py
rbltracker/api/contact_group.py
rbltracker/api/contact_groups.py
rbltracker/api/contacts.py
rbltracker/api/host.py
rbltracker/api/hosts.py
rbltracker/api/listings.py
rbltracker/api/monitoring_profile.py
rbltracker/api/monitoring_profiles.py
rbltracker/api/rbl.py
rbltracker/api/rbl_profile.py
rbltracker/api/rbl_profiles.py
rbltracker/api/rbls.py
rbltracker/api/requesthandler.py
rbltracker/exception/__init__.py
rbltracker/exception/exception.py
rbltracker-1.1.0.dist-info/LICENSE
rbltracker-1.1.0.dist-info/METADATA
rbltracker-1.1.0.dist-info/WHEEL
rbltracker-1.1.0.dist-info/top_level.txt
rbltracker-1.1.0.dist-info/RECORD
