Metadata-Version: 2.1
Name: rbltracker
Version: 1.1.0
Summary: A Python wrapper for the RBLTracker API
Home-page: https://rbltracker.com/
Author: Mike Pultz
Author-email: mike@mikepultz.com
License: MIT
Classifier: Development Status :: 5 - Production/Stable
Classifier: Intended Audience :: Developers
Classifier: License :: OSI Approved :: MIT License
Classifier: Operating System :: OS Independent
Classifier: Programming Language :: Python :: 2.6
Classifier: Programming Language :: Python :: 2.7
Classifier: Programming Language :: Python :: 3.2
Classifier: Programming Language :: Python :: 3.3
Classifier: Programming Language :: Python :: 3.4
Classifier: Topic :: Software Development :: Libraries :: Python Modules
License-File: LICENSE
Requires-Dist: requests >=2.1.0
Requires-Dist: six >=1.9.0
